[
  {
    "glyph_id": 63114,
    "page_number": 390,
    "line_number": 1,
    "sura": 28,
    "ayah": 36,
    "word_position": 1,
    "min_x": 1698,
    "max_x": 1824,
    "min_y": 65,
    "max_y": 163
  },
  {
    "glyph_id": 63115,
    "page_number": 390,
    "line_number": 1,
    "sura": 28,
    "ayah": 36,
    "word_position": 2,
    "min_x": 1459,
    "max_x": 1690,
    "min_y": 65,
    "max_y": 214
  },
  {
    "glyph_id": 63116,
    "page_number": 390,
    "line_number": 1,
    "sura": 28,
    "ayah": 36,
    "word_position": 3,
    "min_x": 1208,
    "max_x": 1447,
    "min_y": 58,
    "max_y": 186
  },
  {
    "glyph_id": 63117,
    "page_number": 390,
    "line_number": 1,
    "sura": 28,
    "ayah": 36,
    "word_position": 4,
    "min_x": 983,
    "max_x": 1197,
    "min_y": 69,
    "max_y": 193
  },
  {
    "glyph_id": 63118,
    "page_number": 390,
    "line_number": 1,
    "sura": 28,
    "ayah": 36,
    "word_position": 5,
    "min_x": 770,
    "max_x": 968,
    "min_y": 76,
    "max_y": 202
  },
  {
    "glyph_id": 63119,
    "page_number": 390,
    "line_number": 1,
    "sura": 28,
    "ayah": 36,
    "word_position": 6,
    "min_x": 614,
    "max_x": 752,
    "min_y": 51,
    "max_y": 186
  },
  {
    "glyph_id": 63120,
    "page_number": 390,
    "line_number": 1,
    "sura": 28,
    "ayah": 36,
    "word_position": 7,
    "min_x": 537,
    "max_x": 599,
    "min_y": 69,
    "max_y": 162
  },
  {
    "glyph_id": 63121,
    "page_number": 390,
    "line_number": 1,
    "sura": 28,
    "ayah": 36,
    "word_position": 8,
    "min_x": 367,
    "max_x": 525,
    "min_y": 67,
    "max_y": 164
  },
  {
    "glyph_id": 63122,
    "page_number": 390,
    "line_number": 1,
    "sura": 28,
    "ayah": 36,
    "word_position": 9,
    "min_x": 271,
    "max_x": 355,
    "min_y": 45,
    "max_y": 191
  },
  {
    "glyph_id": 63123,
    "page_number": 390,
    "line_number": 1,
    "sura": 28,
    "ayah": 36,
    "word_position": 10,
    "min_x": 97,
    "max_x": 264,
    "min_y": 70,
    "max_y": 188
  },
  {
    "glyph_id": 63124,
    "page_number": 390,
    "line_number": 2,
    "sura": 28,
    "ayah": 36,
    "word_position": 11,
    "min_x": 1617,
    "max_x": 1826,
    "min_y": 249,
    "max_y": 377
  },
  {
    "glyph_id": 63125,
    "page_number": 390,
    "line_number": 2,
    "sura": 28,
    "ayah": 36,
    "word_position": 12,
    "min_x": 1497,
    "max_x": 1600,
    "min_y": 268,
    "max_y": 386
  },
  {
    "glyph_id": 63126,
    "page_number": 390,
    "line_number": 2,
    "sura": 28,
    "ayah": 36,
    "word_position": 13,
    "min_x": 1248,
    "max_x": 1486,
    "min_y": 275,
    "max_y": 387
  },
  {
    "glyph_id": 63127,
    "page_number": 390,
    "line_number": 2,
    "sura": 28,
    "ayah": 36,
    "word_position": 14,
    "min_x": 1047,
    "max_x": 1237,
    "min_y": 266,
    "max_y": 400
  },
  {
    "glyph_id": 63128,
    "page_number": 390,
    "line_number": 2,
    "sura": 28,
    "ayah": 36,
    "word_position": 15,
    "min_x": 954,
    "max_x": 1035,
    "min_y": 295,
    "max_y": 395
  },
  {
    "glyph_id": 63129,
    "page_number": 390,
    "line_number": 2,
    "sura": 28,
    "ayah": 36,
    "word_position": 16,
    "min_x": 720,
    "max_x": 950,
    "min_y": 268,
    "max_y": 400
  },
  {
    "glyph_id": 63130,
    "page_number": 390,
    "line_number": 2,
    "sura": 28,
    "ayah": 36,
    "word_position": 17,
    "min_x": 458,
    "max_x": 705,
    "min_y": 249,
    "max_y": 404
  },
  {
    "glyph_id": 63131,
    "page_number": 390,
    "line_number": 2,
    "sura": 28,
    "ayah": 36,
    "word_position": 18,
    "min_x": 268,
    "max_x": 421,
    "min_y": 255,
    "max_y": 397
  },
  {
    "glyph_id": 63132,
    "page_number": 390,
    "line_number": 2,
    "sura": 28,
    "ayah": 37,
    "word_position": 1,
    "min_x": 103,
    "max_x": 269,
    "min_y": 261,
    "max_y": 385
  },
  {
    "glyph_id": 63133,
    "page_number": 390,
    "line_number": 3,
    "sura": 28,
    "ayah": 37,
    "word_position": 2,
    "min_x": 1654,
    "max_x": 1829,
    "min_y": 472,
    "max_y": 591
  },
  {
    "glyph_id": 63134,
    "page_number": 390,
    "line_number": 3,
    "sura": 28,
    "ayah": 37,
    "word_position": 3,
    "min_x": 1515,
    "max_x": 1636,
    "min_y": 475,
    "max_y": 613
  },
  {
    "glyph_id": 63135,
    "page_number": 390,
    "line_number": 3,
    "sura": 28,
    "ayah": 37,
    "word_position": 4,
    "min_x": 1362,
    "max_x": 1505,
    "min_y": 455,
    "max_y": 620
  },
  {
    "glyph_id": 63136,
    "page_number": 390,
    "line_number": 3,
    "sura": 28,
    "ayah": 37,
    "word_position": 5,
    "min_x": 1218,
    "max_x": 1345,
    "min_y": 480,
    "max_y": 603
  },
  {
    "glyph_id": 63137,
    "page_number": 390,
    "line_number": 3,
    "sura": 28,
    "ayah": 37,
    "word_position": 6,
    "min_x": 1042,
    "max_x": 1213,
    "min_y": 460,
    "max_y": 578
  },
  {
    "glyph_id": 63138,
    "page_number": 390,
    "line_number": 3,
    "sura": 28,
    "ayah": 37,
    "word_position": 7,
    "min_x": 753,
    "max_x": 1020,
    "min_y": 454,
    "max_y": 600
  },
  {
    "glyph_id": 63139,
    "page_number": 390,
    "line_number": 3,
    "sura": 28,
    "ayah": 37,
    "word_position": 8,
    "min_x": 642,
    "max_x": 735,
    "min_y": 480,
    "max_y": 592
  },
  {
    "glyph_id": 63140,
    "page_number": 390,
    "line_number": 3,
    "sura": 28,
    "ayah": 37,
    "word_position": 9,
    "min_x": 411,
    "max_x": 632,
    "min_y": 513,
    "max_y": 595
  },
  {
    "glyph_id": 63141,
    "page_number": 390,
    "line_number": 3,
    "sura": 28,
    "ayah": 37,
    "word_position": 10,
    "min_x": 266,
    "max_x": 393,
    "min_y": 483,
    "max_y": 588
  },
  {
    "glyph_id": 63142,
    "page_number": 390,
    "line_number": 3,
    "sura": 28,
    "ayah": 37,
    "word_position": 11,
    "min_x": 100,
    "max_x": 256,
    "min_y": 450,
    "max_y": 593
  },
  {
    "glyph_id": 63143,
    "page_number": 390,
    "line_number": 4,
    "sura": 28,
    "ayah": 37,
    "word_position": 12,
    "min_x": 1749,
    "max_x": 1827,
    "min_y": 656,
    "max_y": 770
  },
  {
    "glyph_id": 63144,
    "page_number": 390,
    "line_number": 4,
    "sura": 28,
    "ayah": 37,
    "word_position": 13,
    "min_x": 1542,
    "max_x": 1747,
    "min_y": 655,
    "max_y": 796
  },
  {
    "glyph_id": 63145,
    "page_number": 390,
    "line_number": 4,
    "sura": 28,
    "ayah": 37,
    "word_position": 14,
    "min_x": 1355,
    "max_x": 1528,
    "min_y": 649,
    "max_y": 809
  },
  {
    "glyph_id": 63146,
    "page_number": 390,
    "line_number": 4,
    "sura": 28,
    "ayah": 37,
    "word_position": 15,
    "min_x": 1357,
    "max_x": 1353,
    "min_y": 656,
    "max_y": 693
  },
  {
    "glyph_id": 63147,
    "page_number": 390,
    "line_number": 4,
    "sura": 28,
    "ayah": 37,
    "word_position": 16,
    "min_x": 1217,
    "max_x": 1347,
    "min_y": 662,
    "max_y": 803
  },
  {
    "glyph_id": 63148,
    "page_number": 390,
    "line_number": 4,
    "sura": 28,
    "ayah": 37,
    "word_position": 17,
    "min_x": 1155,
    "max_x": 1217,
    "min_y": 659,
    "max_y": 769
  },
  {
    "glyph_id": 63149,
    "page_number": 390,
    "line_number": 4,
    "sura": 28,
    "ayah": 37,
    "word_position": 18,
    "min_x": 987,
    "max_x": 1154,
    "min_y": 662,
    "max_y": 822
  },
  {
    "glyph_id": 63150,
    "page_number": 390,
    "line_number": 4,
    "sura": 28,
    "ayah": 37,
    "word_position": 19,
    "min_x": 611,
    "max_x": 975,
    "min_y": 650,
    "max_y": 792
  },
  {
    "glyph_id": 63151,
    "page_number": 390,
    "line_number": 4,
    "sura": 28,
    "ayah": 37,
    "word_position": 20,
    "min_x": 452,
    "max_x": 605,
    "min_y": 657,
    "max_y": 799
  },
  {
    "glyph_id": 63152,
    "page_number": 390,
    "line_number": 4,
    "sura": 28,
    "ayah": 38,
    "word_position": 1,
    "min_x": 298,
    "max_x": 453,
    "min_y": 664,
    "max_y": 786
  },
  {
    "glyph_id": 63153,
    "page_number": 390,
    "line_number": 4,
    "sura": 28,
    "ayah": 38,
    "word_position": 2,
    "min_x": 95,
    "max_x": 286,
    "min_y": 666,
    "max_y": 800
  },
  {
    "glyph_id": 63154,
    "page_number": 390,
    "line_number": 5,
    "sura": 28,
    "ayah": 38,
    "word_position": 3,
    "min_x": 1597,
    "max_x": 1824,
    "min_y": 851,
    "max_y": 989
  },
  {
    "glyph_id": 63155,
    "page_number": 390,
    "line_number": 5,
    "sura": 28,
    "ayah": 38,
    "word_position": 4,
    "min_x": 1382,
    "max_x": 1574,
    "min_y": 850,
    "max_y": 978
  },
  {
    "glyph_id": 63156,
    "page_number": 390,
    "line_number": 5,
    "sura": 28,
    "ayah": 38,
    "word_position": 5,
    "min_x": 1319,
    "max_x": 1380,
    "min_y": 868,
    "max_y": 967
  },
  {
    "glyph_id": 63157,
    "page_number": 390,
    "line_number": 5,
    "sura": 28,
    "ayah": 38,
    "word_position": 6,
    "min_x": 1099,
    "max_x": 1306,
    "min_y": 873,
    "max_y": 996
  },
  {
    "glyph_id": 63158,
    "page_number": 390,
    "line_number": 5,
    "sura": 28,
    "ayah": 38,
    "word_position": 7,
    "min_x": 820,
    "max_x": 1074,
    "min_y": 868,
    "max_y": 1023
  },
  {
    "glyph_id": 63159,
    "page_number": 390,
    "line_number": 5,
    "sura": 28,
    "ayah": 38,
    "word_position": 8,
    "min_x": 718,
    "max_x": 803,
    "min_y": 883,
    "max_y": 1005
  },
  {
    "glyph_id": 63160,
    "page_number": 390,
    "line_number": 5,
    "sura": 28,
    "ayah": 38,
    "word_position": 9,
    "min_x": 570,
    "max_x": 703,
    "min_y": 864,
    "max_y": 1003
  },
  {
    "glyph_id": 63161,
    "page_number": 390,
    "line_number": 5,
    "sura": 28,
    "ayah": 38,
    "word_position": 10,
    "min_x": 296,
    "max_x": 554,
    "min_y": 864,
    "max_y": 1002
  },
  {
    "glyph_id": 63162,
    "page_number": 390,
    "line_number": 5,
    "sura": 28,
    "ayah": 38,
    "word_position": 11,
    "min_x": 105,
    "max_x": 284,
    "min_y": 847,
    "max_y": 989
  },
  {
    "glyph_id": 63163,
    "page_number": 390,
    "line_number": 6,
    "sura": 28,
    "ayah": 38,
    "word_position": 12,
    "min_x": 1762,
    "max_x": 1826,
    "min_y": 1088,
    "max_y": 1195
  },
  {
    "glyph_id": 63164,
    "page_number": 390,
    "line_number": 6,
    "sura": 28,
    "ayah": 38,
    "word_position": 13,
    "min_x": 1488,
    "max_x": 1745,
    "min_y": 1076,
    "max_y": 1191
  },
  {
    "glyph_id": 63165,
    "page_number": 390,
    "line_number": 6,
    "sura": 28,
    "ayah": 38,
    "word_position": 14,
    "min_x": 1373,
    "max_x": 1473,
    "min_y": 1069,
    "max_y": 1189
  },
  {
    "glyph_id": 63166,
    "page_number": 390,
    "line_number": 6,
    "sura": 28,
    "ayah": 38,
    "word_position": 15,
    "min_x": 1161,
    "max_x": 1356,
    "min_y": 1065,
    "max_y": 1199
  },
  {
    "glyph_id": 63167,
    "page_number": 390,
    "line_number": 6,
    "sura": 28,
    "ayah": 38,
    "word_position": 16,
    "min_x": 899,
    "max_x": 1145,
    "min_y": 1065,
    "max_y": 1190
  },
  {
    "glyph_id": 63168,
    "page_number": 390,
    "line_number": 6,
    "sura": 28,
    "ayah": 38,
    "word_position": 17,
    "min_x": 819,
    "max_x": 887,
    "min_y": 1074,
    "max_y": 1203
  },
  {
    "glyph_id": 63169,
    "page_number": 390,
    "line_number": 6,
    "sura": 28,
    "ayah": 38,
    "word_position": 18,
    "min_x": 580,
    "max_x": 805,
    "min_y": 1077,
    "max_y": 1190
  },
  {
    "glyph_id": 63170,
    "page_number": 390,
    "line_number": 6,
    "sura": 28,
    "ayah": 38,
    "word_position": 19,
    "min_x": 372,
    "max_x": 552,
    "min_y": 1046,
    "max_y": 1212
  },
  {
    "glyph_id": 63171,
    "page_number": 390,
    "line_number": 6,
    "sura": 28,
    "ayah": 38,
    "word_position": 20,
    "min_x": 210,
    "max_x": 359,
    "min_y": 1044,
    "max_y": 1223
  },
  {
    "glyph_id": 63172,
    "page_number": 390,
    "line_number": 6,
    "sura": 28,
    "ayah": 38,
    "word_position": 21,
    "min_x": 102,
    "max_x": 187,
    "min_y": 1065,
    "max_y": 1206
  },
  {
    "glyph_id": 63173,
    "page_number": 390,
    "line_number": 7,
    "sura": 28,
    "ayah": 38,
    "word_position": 22,
    "min_x": 1695,
    "max_x": 1824,
    "min_y": 1269,
    "max_y": 1406
  },
  {
    "glyph_id": 63174,
    "page_number": 390,
    "line_number": 7,
    "sura": 28,
    "ayah": 38,
    "word_position": 23,
    "min_x": 1427,
    "max_x": 1682,
    "min_y": 1277,
    "max_y": 1394
  },
  {
    "glyph_id": 63175,
    "page_number": 390,
    "line_number": 7,
    "sura": 28,
    "ayah": 38,
    "word_position": 24,
    "min_x": 1266,
    "max_x": 1416,
    "min_y": 1278,
    "max_y": 1410
  },
  {
    "glyph_id": 63176,
    "page_number": 390,
    "line_number": 7,
    "sura": 28,
    "ayah": 38,
    "word_position": 25,
    "min_x": 1027,
    "max_x": 1255,
    "min_y": 1250,
    "max_y": 1372
  },
  {
    "glyph_id": 63177,
    "page_number": 390,
    "line_number": 7,
    "sura": 28,
    "ayah": 38,
    "word_position": 26,
    "min_x": 857,
    "max_x": 1022,
    "min_y": 1290,
    "max_y": 1397
  },
  {
    "glyph_id": 63178,
    "page_number": 390,
    "line_number": 7,
    "sura": 28,
    "ayah": 38,
    "word_position": 27,
    "min_x": 575,
    "max_x": 848,
    "min_y": 1270,
    "max_y": 1410
  },
  {
    "glyph_id": 63179,
    "page_number": 390,
    "line_number": 7,
    "sura": 28,
    "ayah": 38,
    "word_position": 28,
    "min_x": 413,
    "max_x": 566,
    "min_y": 1260,
    "max_y": 1402
  },
  {
    "glyph_id": 63180,
    "page_number": 390,
    "line_number": 7,
    "sura": 28,
    "ayah": 39,
    "word_position": 1,
    "min_x": 94,
    "max_x": 414,
    "min_y": 1273,
    "max_y": 1388
  },
  {
    "glyph_id": 63181,
    "page_number": 390,
    "line_number": 8,
    "sura": 28,
    "ayah": 39,
    "word_position": 2,
    "min_x": 1718,
    "max_x": 1828,
    "min_y": 1473,
    "max_y": 1596
  },
  {
    "glyph_id": 63182,
    "page_number": 390,
    "line_number": 8,
    "sura": 28,
    "ayah": 39,
    "word_position": 3,
    "min_x": 1427,
    "max_x": 1716,
    "min_y": 1479,
    "max_y": 1597
  },
  {
    "glyph_id": 63183,
    "page_number": 390,
    "line_number": 8,
    "sura": 28,
    "ayah": 39,
    "word_position": 4,
    "min_x": 1282,
    "max_x": 1423,
    "min_y": 1495,
    "max_y": 1601
  },
  {
    "glyph_id": 63184,
    "page_number": 390,
    "line_number": 8,
    "sura": 28,
    "ayah": 39,
    "word_position": 5,
    "min_x": 1044,
    "max_x": 1270,
    "min_y": 1458,
    "max_y": 1601
  },
  {
    "glyph_id": 63185,
    "page_number": 390,
    "line_number": 8,
    "sura": 28,
    "ayah": 39,
    "word_position": 6,
    "min_x": 845,
    "max_x": 1028,
    "min_y": 1477,
    "max_y": 1609
  },
  {
    "glyph_id": 63186,
    "page_number": 390,
    "line_number": 8,
    "sura": 28,
    "ayah": 39,
    "word_position": 7,
    "min_x": 667,
    "max_x": 841,
    "min_y": 1466,
    "max_y": 1608
  },
  {
    "glyph_id": 63187,
    "page_number": 390,
    "line_number": 8,
    "sura": 28,
    "ayah": 39,
    "word_position": 8,
    "min_x": 444,
    "max_x": 651,
    "min_y": 1456,
    "max_y": 1596
  },
  {
    "glyph_id": 63188,
    "page_number": 390,
    "line_number": 8,
    "sura": 28,
    "ayah": 39,
    "word_position": 9,
    "min_x": 281,
    "max_x": 436,
    "min_y": 1458,
    "max_y": 1628
  },
  {
    "glyph_id": 63189,
    "page_number": 390,
    "line_number": 8,
    "sura": 28,
    "ayah": 39,
    "word_position": 10,
    "min_x": 100,
    "max_x": 268,
    "min_y": 1468,
    "max_y": 1602
  },
  {
    "glyph_id": 63190,
    "page_number": 390,
    "line_number": 9,
    "sura": 28,
    "ayah": 39,
    "word_position": 11,
    "min_x": 1759,
    "max_x": 1821,
    "min_y": 1669,
    "max_y": 1773
  },
  {
    "glyph_id": 63191,
    "page_number": 390,
    "line_number": 9,
    "sura": 28,
    "ayah": 39,
    "word_position": 12,
    "min_x": 1391,
    "max_x": 1751,
    "min_y": 1673,
    "max_y": 1799
  },
  {
    "glyph_id": 63192,
    "page_number": 390,
    "line_number": 9,
    "sura": 28,
    "ayah": 39,
    "word_position": 13,
    "min_x": 1207,
    "max_x": 1360,
    "min_y": 1662,
    "max_y": 1804
  },
  {
    "glyph_id": 63193,
    "page_number": 390,
    "line_number": 9,
    "sura": 28,
    "ayah": 40,
    "word_position": 1,
    "min_x": 850,
    "max_x": 1208,
    "min_y": 1651,
    "max_y": 1774
  },
  {
    "glyph_id": 63194,
    "page_number": 390,
    "line_number": 9,
    "sura": 28,
    "ayah": 40,
    "word_position": 2,
    "min_x": 530,
    "max_x": 838,
    "min_y": 1676,
    "max_y": 1797
  },
  {
    "glyph_id": 63195,
    "page_number": 390,
    "line_number": 9,
    "sura": 28,
    "ayah": 40,
    "word_position": 3,
    "min_x": 187,
    "max_x": 517,
    "min_y": 1670,
    "max_y": 1830
  },
  {
    "glyph_id": 63196,
    "page_number": 390,
    "line_number": 9,
    "sura": 28,
    "ayah": 40,
    "word_position": 4,
    "min_x": 102,
    "max_x": 171,
    "min_y": 1703,
    "max_y": 1807
  },
  {
    "glyph_id": 63197,
    "page_number": 390,
    "line_number": 10,
    "sura": 28,
    "ayah": 40,
    "word_position": 5,
    "min_x": 1665,
    "max_x": 1823,
    "min_y": 1876,
    "max_y": 2007
  },
  {
    "glyph_id": 63198,
    "page_number": 390,
    "line_number": 10,
    "sura": 28,
    "ayah": 40,
    "word_position": 6,
    "min_x": 1668,
    "max_x": 1665,
    "min_y": 1851,
    "max_y": 1888
  },
  {
    "glyph_id": 63199,
    "page_number": 390,
    "line_number": 10,
    "sura": 28,
    "ayah": 40,
    "word_position": 7,
    "min_x": 1413,
    "max_x": 1660,
    "min_y": 1858,
    "max_y": 1994
  },
  {
    "glyph_id": 63200,
    "page_number": 390,
    "line_number": 10,
    "sura": 28,
    "ayah": 40,
    "word_position": 8,
    "min_x": 1252,
    "max_x": 1410,
    "min_y": 1864,
    "max_y": 1998
  },
  {
    "glyph_id": 63201,
    "page_number": 390,
    "line_number": 10,
    "sura": 28,
    "ayah": 40,
    "word_position": 9,
    "min_x": 907,
    "max_x": 1243,
    "min_y": 1875,
    "max_y": 1977
  },
  {
    "glyph_id": 63202,
    "page_number": 390,
    "line_number": 10,
    "sura": 28,
    "ayah": 40,
    "word_position": 10,
    "min_x": 688,
    "max_x": 896,
    "min_y": 1859,
    "max_y": 1999
  },
  {
    "glyph_id": 63203,
    "page_number": 390,
    "line_number": 10,
    "sura": 28,
    "ayah": 40,
    "word_position": 11,
    "min_x": 266,
    "max_x": 676,
    "min_y": 1851,
    "max_y": 2003
  },
  {
    "glyph_id": 63204,
    "page_number": 390,
    "line_number": 10,
    "sura": 28,
    "ayah": 40,
    "word_position": 12,
    "min_x": 100,
    "max_x": 253,
    "min_y": 1863,
    "max_y": 2005
  },
  {
    "glyph_id": 63205,
    "page_number": 390,
    "line_number": 11,
    "sura": 28,
    "ayah": 41,
    "word_position": 1,
    "min_x": 1463,
    "max_x": 1824,
    "min_y": 2080,
    "max_y": 2227
  },
  {
    "glyph_id": 63206,
    "page_number": 390,
    "line_number": 11,
    "sura": 28,
    "ayah": 41,
    "word_position": 2,
    "min_x": 1265,
    "max_x": 1445,
    "min_y": 2060,
    "max_y": 2216
  },
  {
    "glyph_id": 63207,
    "page_number": 390,
    "line_number": 11,
    "sura": 28,
    "ayah": 41,
    "word_position": 3,
    "min_x": 889,
    "max_x": 1246,
    "min_y": 2076,
    "max_y": 2197
  },
  {
    "glyph_id": 63208,
    "page_number": 390,
    "line_number": 11,
    "sura": 28,
    "ayah": 41,
    "word_position": 4,
    "min_x": 783,
    "max_x": 871,
    "min_y": 2070,
    "max_y": 2213
  },
  {
    "glyph_id": 63209,
    "page_number": 390,
    "line_number": 11,
    "sura": 28,
    "ayah": 41,
    "word_position": 5,
    "min_x": 537,
    "max_x": 766,
    "min_y": 2069,
    "max_y": 2210
  },
  {
    "glyph_id": 63210,
    "page_number": 390,
    "line_number": 11,
    "sura": 28,
    "ayah": 41,
    "word_position": 6,
    "min_x": 544,
    "max_x": 533,
    "min_y": 2063,
    "max_y": 2100
  },
  {
    "glyph_id": 63211,
    "page_number": 390,
    "line_number": 11,
    "sura": 28,
    "ayah": 41,
    "word_position": 7,
    "min_x": 378,
    "max_x": 527,
    "min_y": 2087,
    "max_y": 2230
  },
  {
    "glyph_id": 63212,
    "page_number": 390,
    "line_number": 11,
    "sura": 28,
    "ayah": 41,
    "word_position": 8,
    "min_x": 101,
    "max_x": 362,
    "min_y": 2072,
    "max_y": 2201
  },
  {
    "glyph_id": 63213,
    "page_number": 390,
    "line_number": 12,
    "sura": 28,
    "ayah": 41,
    "word_position": 9,
    "min_x": 1762,
    "max_x": 1826,
    "min_y": 2270,
    "max_y": 2375
  },
  {
    "glyph_id": 63214,
    "page_number": 390,
    "line_number": 12,
    "sura": 28,
    "ayah": 41,
    "word_position": 10,
    "min_x": 1391,
    "max_x": 1755,
    "min_y": 2270,
    "max_y": 2400
  },
  {
    "glyph_id": 63215,
    "page_number": 390,
    "line_number": 12,
    "sura": 28,
    "ayah": 41,
    "word_position": 11,
    "min_x": 1209,
    "max_x": 1362,
    "min_y": 2265,
    "max_y": 2407
  },
  {
    "glyph_id": 63216,
    "page_number": 390,
    "line_number": 12,
    "sura": 28,
    "ayah": 42,
    "word_position": 1,
    "min_x": 814,
    "max_x": 1210,
    "min_y": 2260,
    "max_y": 2431
  },
  {
    "glyph_id": 63217,
    "page_number": 390,
    "line_number": 12,
    "sura": 28,
    "ayah": 42,
    "word_position": 2,
    "min_x": 731,
    "max_x": 797,
    "min_y": 2299,
    "max_y": 2408
  },
  {
    "glyph_id": 63218,
    "page_number": 390,
    "line_number": 12,
    "sura": 28,
    "ayah": 42,
    "word_position": 3,
    "min_x": 528,
    "max_x": 720,
    "min_y": 2277,
    "max_y": 2405
  },
  {
    "glyph_id": 63219,
    "page_number": 390,
    "line_number": 12,
    "sura": 28,
    "ayah": 42,
    "word_position": 4,
    "min_x": 352,
    "max_x": 515,
    "min_y": 2258,
    "max_y": 2393
  },
  {
    "glyph_id": 63220,
    "page_number": 390,
    "line_number": 12,
    "sura": 28,
    "ayah": 42,
    "word_position": 5,
    "min_x": 106,
    "max_x": 334,
    "min_y": 2268,
    "max_y": 2380
  },
  {
    "glyph_id": 63221,
    "page_number": 390,
    "line_number": 12,
    "sura": 28,
    "ayah": 42,
    "word_position": 6,
    "min_x": 118,
    "max_x": 108,
    "min_y": 2234,
    "max_y": 2270
  },
  {
    "glyph_id": 63222,
    "page_number": 390,
    "line_number": 13,
    "sura": 28,
    "ayah": 42,
    "word_position": 7,
    "min_x": 1677,
    "max_x": 1827,
    "min_y": 2488,
    "max_y": 2624
  },
  {
    "glyph_id": 63223,
    "page_number": 390,
    "line_number": 13,
    "sura": 28,
    "ayah": 42,
    "word_position": 8,
    "min_x": 1396,
    "max_x": 1666,
    "min_y": 2476,
    "max_y": 2604
  },
  {
    "glyph_id": 63224,
    "page_number": 390,
    "line_number": 13,
    "sura": 28,
    "ayah": 42,
    "word_position": 9,
    "min_x": 1259,
    "max_x": 1379,
    "min_y": 2477,
    "max_y": 2628
  },
  {
    "glyph_id": 63225,
    "page_number": 390,
    "line_number": 13,
    "sura": 28,
    "ayah": 42,
    "word_position": 10,
    "min_x": 1051,
    "max_x": 1238,
    "min_y": 2495,
    "max_y": 2604
  },
  {
    "glyph_id": 63226,
    "page_number": 390,
    "line_number": 13,
    "sura": 28,
    "ayah": 42,
    "word_position": 11,
    "min_x": 652,
    "max_x": 1035,
    "min_y": 2466,
    "max_y": 2600
  },
  {
    "glyph_id": 63227,
    "page_number": 390,
    "line_number": 13,
    "sura": 28,
    "ayah": 42,
    "word_position": 12,
    "min_x": 474,
    "max_x": 627,
    "min_y": 2466,
    "max_y": 2608
  },
  {
    "glyph_id": 63228,
    "page_number": 390,
    "line_number": 13,
    "sura": 28,
    "ayah": 43,
    "word_position": 1,
    "min_x": 305,
    "max_x": 475,
    "min_y": 2468,
    "max_y": 2597
  },
  {
    "glyph_id": 63229,
    "page_number": 390,
    "line_number": 13,
    "sura": 28,
    "ayah": 43,
    "word_position": 2,
    "min_x": 99,
    "max_x": 292,
    "min_y": 2470,
    "max_y": 2595
  },
  {
    "glyph_id": 63230,
    "page_number": 390,
    "line_number": 14,
    "sura": 28,
    "ayah": 43,
    "word_position": 3,
    "min_x": 1649,
    "max_x": 1825,
    "min_y": 2690,
    "max_y": 2802
  },
  {
    "glyph_id": 63231,
    "page_number": 390,
    "line_number": 14,
    "sura": 28,
    "ayah": 43,
    "word_position": 4,
    "min_x": 1237,
    "max_x": 1636,
    "min_y": 2677,
    "max_y": 2801
  },
  {
    "glyph_id": 63232,
    "page_number": 390,
    "line_number": 14,
    "sura": 28,
    "ayah": 43,
    "word_position": 5,
    "min_x": 1122,
    "max_x": 1211,
    "min_y": 2681,
    "max_y": 2810
  },
  {
    "glyph_id": 63233,
    "page_number": 390,
    "line_number": 14,
    "sura": 28,
    "ayah": 43,
    "word_position": 6,
    "min_x": 974,
    "max_x": 1106,
    "min_y": 2684,
    "max_y": 2802
  },
  {
    "glyph_id": 63234,
    "page_number": 390,
    "line_number": 14,
    "sura": 28,
    "ayah": 43,
    "word_position": 7,
    "min_x": 879,
    "max_x": 951,
    "min_y": 2676,
    "max_y": 2779
  },
  {
    "glyph_id": 63235,
    "page_number": 390,
    "line_number": 14,
    "sura": 28,
    "ayah": 43,
    "word_position": 8,
    "min_x": 636,
    "max_x": 868,
    "min_y": 2660,
    "max_y": 2778
  },
  {
    "glyph_id": 63236,
    "page_number": 390,
    "line_number": 14,
    "sura": 28,
    "ayah": 43,
    "word_position": 9,
    "min_x": 293,
    "max_x": 613,
    "min_y": 2670,
    "max_y": 2802
  },
  {
    "glyph_id": 63237,
    "page_number": 390,
    "line_number": 14,
    "sura": 28,
    "ayah": 43,
    "word_position": 10,
    "min_x": 101,
    "max_x": 276,
    "min_y": 2652,
    "max_y": 2802
  },
  {
    "glyph_id": 63238,
    "page_number": 390,
    "line_number": 15,
    "sura": 28,
    "ayah": 43,
    "word_position": 11,
    "min_x": 1556,
    "max_x": 1823,
    "min_y": 2881,
    "max_y": 3016
  },
  {
    "glyph_id": 63239,
    "page_number": 390,
    "line_number": 15,
    "sura": 28,
    "ayah": 43,
    "word_position": 12,
    "min_x": 1340,
    "max_x": 1552,
    "min_y": 2872,
    "max_y": 3005
  },
  {
    "glyph_id": 63240,
    "page_number": 390,
    "line_number": 15,
    "sura": 28,
    "ayah": 43,
    "word_position": 13,
    "min_x": 1089,
    "max_x": 1326,
    "min_y": 2876,
    "max_y": 3000
  },
  {
    "glyph_id": 63241,
    "page_number": 390,
    "line_number": 15,
    "sura": 28,
    "ayah": 43,
    "word_position": 14,
    "min_x": 830,
    "max_x": 1076,
    "min_y": 2860,
    "max_y": 2996
  },
  {
    "glyph_id": 63242,
    "page_number": 390,
    "line_number": 15,
    "sura": 28,
    "ayah": 43,
    "word_position": 15,
    "min_x": 598,
    "max_x": 813,
    "min_y": 2845,
    "max_y": 3030
  },
  {
    "glyph_id": 63243,
    "page_number": 390,
    "line_number": 15,
    "sura": 28,
    "ayah": 43,
    "word_position": 16,
    "min_x": 301,
    "max_x": 586,
    "min_y": 2847,
    "max_y": 3003
  },
  {
    "glyph_id": 63244,
    "page_number": 390,
    "line_number": 15,
    "sura": 28,
    "ayah": 43,
    "word_position": 17,
    "min_x": 103,
    "max_x": 256,
    "min_y": 2868,
    "max_y": 3010
  }
]