[
  {
    "glyph_id": 79155,
    "page_number": 488,
    "line_number": 1,
    "sura": 42,
    "ayah": 45,
    "word_position": 1,
    "min_x": 1586,
    "max_x": 1824,
    "min_y": 76,
    "max_y": 227
  },
  {
    "glyph_id": 79156,
    "page_number": 488,
    "line_number": 1,
    "sura": 42,
    "ayah": 45,
    "word_position": 2,
    "min_x": 1289,
    "max_x": 1573,
    "min_y": 74,
    "max_y": 203
  },
  {
    "glyph_id": 79157,
    "page_number": 488,
    "line_number": 1,
    "sura": 42,
    "ayah": 45,
    "word_position": 3,
    "min_x": 1081,
    "max_x": 1273,
    "min_y": 75,
    "max_y": 202
  },
  {
    "glyph_id": 79158,
    "page_number": 488,
    "line_number": 1,
    "sura": 42,
    "ayah": 45,
    "word_position": 4,
    "min_x": 702,
    "max_x": 1075,
    "min_y": 79,
    "max_y": 203
  },
  {
    "glyph_id": 79159,
    "page_number": 488,
    "line_number": 1,
    "sura": 42,
    "ayah": 45,
    "word_position": 5,
    "min_x": 596,
    "max_x": 685,
    "min_y": 90,
    "max_y": 204
  },
  {
    "glyph_id": 79160,
    "page_number": 488,
    "line_number": 1,
    "sura": 42,
    "ayah": 45,
    "word_position": 6,
    "min_x": 434,
    "max_x": 586,
    "min_y": 45,
    "max_y": 204
  },
  {
    "glyph_id": 79161,
    "page_number": 488,
    "line_number": 1,
    "sura": 42,
    "ayah": 45,
    "word_position": 7,
    "min_x": 120,
    "max_x": 419,
    "min_y": 60,
    "max_y": 202
  },
  {
    "glyph_id": 79162,
    "page_number": 488,
    "line_number": 2,
    "sura": 42,
    "ayah": 45,
    "word_position": 8,
    "min_x": 1731,
    "max_x": 1828,
    "min_y": 326,
    "max_y": 405
  },
  {
    "glyph_id": 79163,
    "page_number": 488,
    "line_number": 2,
    "sura": 42,
    "ayah": 45,
    "word_position": 9,
    "min_x": 1535,
    "max_x": 1724,
    "min_y": 282,
    "max_y": 413
  },
  {
    "glyph_id": 79164,
    "page_number": 488,
    "line_number": 2,
    "sura": 42,
    "ayah": 45,
    "word_position": 10,
    "min_x": 1360,
    "max_x": 1526,
    "min_y": 277,
    "max_y": 433
  },
  {
    "glyph_id": 79165,
    "page_number": 488,
    "line_number": 2,
    "sura": 42,
    "ayah": 45,
    "word_position": 11,
    "min_x": 1357,
    "max_x": 1353,
    "min_y": 259,
    "max_y": 297
  },
  {
    "glyph_id": 79166,
    "page_number": 488,
    "line_number": 2,
    "sura": 42,
    "ayah": 45,
    "word_position": 12,
    "min_x": 1188,
    "max_x": 1347,
    "min_y": 271,
    "max_y": 397
  },
  {
    "glyph_id": 79167,
    "page_number": 488,
    "line_number": 2,
    "sura": 42,
    "ayah": 45,
    "word_position": 13,
    "min_x": 1011,
    "max_x": 1175,
    "min_y": 257,
    "max_y": 403
  },
  {
    "glyph_id": 79168,
    "page_number": 488,
    "line_number": 2,
    "sura": 42,
    "ayah": 45,
    "word_position": 14,
    "min_x": 754,
    "max_x": 1000,
    "min_y": 280,
    "max_y": 406
  },
  {
    "glyph_id": 79169,
    "page_number": 488,
    "line_number": 2,
    "sura": 42,
    "ayah": 45,
    "word_position": 15,
    "min_x": 670,
    "max_x": 743,
    "min_y": 271,
    "max_y": 415
  },
  {
    "glyph_id": 79170,
    "page_number": 488,
    "line_number": 2,
    "sura": 42,
    "ayah": 45,
    "word_position": 16,
    "min_x": 298,
    "max_x": 654,
    "min_y": 266,
    "max_y": 422
  },
  {
    "glyph_id": 79171,
    "page_number": 488,
    "line_number": 2,
    "sura": 42,
    "ayah": 45,
    "word_position": 17,
    "min_x": 117,
    "max_x": 275,
    "min_y": 253,
    "max_y": 404
  },
  {
    "glyph_id": 79172,
    "page_number": 488,
    "line_number": 3,
    "sura": 42,
    "ayah": 45,
    "word_position": 18,
    "min_x": 1596,
    "max_x": 1831,
    "min_y": 480,
    "max_y": 605
  },
  {
    "glyph_id": 79173,
    "page_number": 488,
    "line_number": 3,
    "sura": 42,
    "ayah": 45,
    "word_position": 19,
    "min_x": 1332,
    "max_x": 1578,
    "min_y": 459,
    "max_y": 635
  },
  {
    "glyph_id": 79174,
    "page_number": 488,
    "line_number": 3,
    "sura": 42,
    "ayah": 45,
    "word_position": 20,
    "min_x": 1031,
    "max_x": 1315,
    "min_y": 459,
    "max_y": 643
  },
  {
    "glyph_id": 79175,
    "page_number": 488,
    "line_number": 3,
    "sura": 42,
    "ayah": 45,
    "word_position": 21,
    "min_x": 911,
    "max_x": 1018,
    "min_y": 492,
    "max_y": 639
  },
  {
    "glyph_id": 79176,
    "page_number": 488,
    "line_number": 3,
    "sura": 42,
    "ayah": 45,
    "word_position": 22,
    "min_x": 647,
    "max_x": 893,
    "min_y": 476,
    "max_y": 609
  },
  {
    "glyph_id": 79177,
    "page_number": 488,
    "line_number": 3,
    "sura": 42,
    "ayah": 45,
    "word_position": 23,
    "min_x": 641,
    "max_x": 631,
    "min_y": 457,
    "max_y": 495
  },
  {
    "glyph_id": 79178,
    "page_number": 488,
    "line_number": 3,
    "sura": 42,
    "ayah": 45,
    "word_position": 24,
    "min_x": 511,
    "max_x": 625,
    "min_y": 458,
    "max_y": 580
  },
  {
    "glyph_id": 79179,
    "page_number": 488,
    "line_number": 3,
    "sura": 42,
    "ayah": 45,
    "word_position": 25,
    "min_x": 437,
    "max_x": 508,
    "min_y": 472,
    "max_y": 608
  },
  {
    "glyph_id": 79180,
    "page_number": 488,
    "line_number": 3,
    "sura": 42,
    "ayah": 45,
    "word_position": 26,
    "min_x": 120,
    "max_x": 416,
    "min_y": 466,
    "max_y": 604
  },
  {
    "glyph_id": 79181,
    "page_number": 488,
    "line_number": 4,
    "sura": 42,
    "ayah": 45,
    "word_position": 27,
    "min_x": 1767,
    "max_x": 1833,
    "min_y": 707,
    "max_y": 810
  },
  {
    "glyph_id": 79182,
    "page_number": 488,
    "line_number": 4,
    "sura": 42,
    "ayah": 45,
    "word_position": 28,
    "min_x": 1543,
    "max_x": 1756,
    "min_y": 678,
    "max_y": 831
  },
  {
    "glyph_id": 79183,
    "page_number": 488,
    "line_number": 4,
    "sura": 42,
    "ayah": 45,
    "word_position": 29,
    "min_x": 1335,
    "max_x": 1529,
    "min_y": 664,
    "max_y": 825
  },
  {
    "glyph_id": 79184,
    "page_number": 488,
    "line_number": 4,
    "sura": 42,
    "ayah": 45,
    "word_position": 30,
    "min_x": 1164,
    "max_x": 1317,
    "min_y": 669,
    "max_y": 811
  },
  {
    "glyph_id": 79185,
    "page_number": 488,
    "line_number": 4,
    "sura": 42,
    "ayah": 46,
    "word_position": 1,
    "min_x": 1032,
    "max_x": 1165,
    "min_y": 690,
    "max_y": 795
  },
  {
    "glyph_id": 79186,
    "page_number": 488,
    "line_number": 4,
    "sura": 42,
    "ayah": 46,
    "word_position": 2,
    "min_x": 846,
    "max_x": 1018,
    "min_y": 676,
    "max_y": 788
  },
  {
    "glyph_id": 79187,
    "page_number": 488,
    "line_number": 4,
    "sura": 42,
    "ayah": 46,
    "word_position": 3,
    "min_x": 737,
    "max_x": 837,
    "min_y": 669,
    "max_y": 830
  },
  {
    "glyph_id": 79188,
    "page_number": 488,
    "line_number": 4,
    "sura": 42,
    "ayah": 46,
    "word_position": 4,
    "min_x": 623,
    "max_x": 720,
    "min_y": 691,
    "max_y": 801
  },
  {
    "glyph_id": 79189,
    "page_number": 488,
    "line_number": 4,
    "sura": 42,
    "ayah": 46,
    "word_position": 5,
    "min_x": 423,
    "max_x": 614,
    "min_y": 665,
    "max_y": 821
  },
  {
    "glyph_id": 79190,
    "page_number": 488,
    "line_number": 4,
    "sura": 42,
    "ayah": 46,
    "word_position": 6,
    "min_x": 118,
    "max_x": 405,
    "min_y": 673,
    "max_y": 842
  },
  {
    "glyph_id": 79191,
    "page_number": 488,
    "line_number": 5,
    "sura": 42,
    "ayah": 46,
    "word_position": 7,
    "min_x": 1738,
    "max_x": 1832,
    "min_y": 905,
    "max_y": 1012
  },
  {
    "glyph_id": 79192,
    "page_number": 488,
    "line_number": 5,
    "sura": 42,
    "ayah": 46,
    "word_position": 8,
    "min_x": 1594,
    "max_x": 1731,
    "min_y": 887,
    "max_y": 1009
  },
  {
    "glyph_id": 79193,
    "page_number": 488,
    "line_number": 5,
    "sura": 42,
    "ayah": 46,
    "word_position": 9,
    "min_x": 1487,
    "max_x": 1590,
    "min_y": 880,
    "max_y": 1007
  },
  {
    "glyph_id": 79194,
    "page_number": 488,
    "line_number": 5,
    "sura": 42,
    "ayah": 46,
    "word_position": 10,
    "min_x": 1478,
    "max_x": 1484,
    "min_y": 857,
    "max_y": 895
  },
  {
    "glyph_id": 79195,
    "page_number": 488,
    "line_number": 5,
    "sura": 42,
    "ayah": 46,
    "word_position": 11,
    "min_x": 1337,
    "max_x": 1478,
    "min_y": 892,
    "max_y": 1000
  },
  {
    "glyph_id": 79196,
    "page_number": 488,
    "line_number": 5,
    "sura": 42,
    "ayah": 46,
    "word_position": 12,
    "min_x": 1097,
    "max_x": 1328,
    "min_y": 880,
    "max_y": 1022
  },
  {
    "glyph_id": 79197,
    "page_number": 488,
    "line_number": 5,
    "sura": 42,
    "ayah": 46,
    "word_position": 13,
    "min_x": 993,
    "max_x": 1093,
    "min_y": 874,
    "max_y": 983
  },
  {
    "glyph_id": 79198,
    "page_number": 488,
    "line_number": 5,
    "sura": 42,
    "ayah": 46,
    "word_position": 14,
    "min_x": 918,
    "max_x": 986,
    "min_y": 872,
    "max_y": 984
  },
  {
    "glyph_id": 79199,
    "page_number": 488,
    "line_number": 5,
    "sura": 42,
    "ayah": 46,
    "word_position": 15,
    "min_x": 831,
    "max_x": 907,
    "min_y": 870,
    "max_y": 982
  },
  {
    "glyph_id": 79200,
    "page_number": 488,
    "line_number": 5,
    "sura": 42,
    "ayah": 46,
    "word_position": 16,
    "min_x": 737,
    "max_x": 827,
    "min_y": 929,
    "max_y": 1010
  },
  {
    "glyph_id": 79201,
    "page_number": 488,
    "line_number": 5,
    "sura": 42,
    "ayah": 46,
    "word_position": 17,
    "min_x": 569,
    "max_x": 734,
    "min_y": 895,
    "max_y": 1030
  },
  {
    "glyph_id": 79202,
    "page_number": 488,
    "line_number": 5,
    "sura": 42,
    "ayah": 46,
    "word_position": 18,
    "min_x": 417,
    "max_x": 570,
    "min_y": 870,
    "max_y": 1012
  },
  {
    "glyph_id": 79203,
    "page_number": 488,
    "line_number": 5,
    "sura": 42,
    "ayah": 47,
    "word_position": 1,
    "min_x": 117,
    "max_x": 418,
    "min_y": 885,
    "max_y": 1021
  },
  {
    "glyph_id": 79204,
    "page_number": 488,
    "line_number": 6,
    "sura": 42,
    "ayah": 47,
    "word_position": 2,
    "min_x": 1632,
    "max_x": 1837,
    "min_y": 1067,
    "max_y": 1236
  },
  {
    "glyph_id": 79205,
    "page_number": 488,
    "line_number": 6,
    "sura": 42,
    "ayah": 47,
    "word_position": 3,
    "min_x": 1521,
    "max_x": 1615,
    "min_y": 1103,
    "max_y": 1203
  },
  {
    "glyph_id": 79206,
    "page_number": 488,
    "line_number": 6,
    "sura": 42,
    "ayah": 47,
    "word_position": 4,
    "min_x": 1365,
    "max_x": 1511,
    "min_y": 1082,
    "max_y": 1218
  },
  {
    "glyph_id": 79207,
    "page_number": 488,
    "line_number": 6,
    "sura": 42,
    "ayah": 47,
    "word_position": 5,
    "min_x": 1281,
    "max_x": 1355,
    "min_y": 1074,
    "max_y": 1195
  },
  {
    "glyph_id": 79208,
    "page_number": 488,
    "line_number": 6,
    "sura": 42,
    "ayah": 47,
    "word_position": 6,
    "min_x": 1139,
    "max_x": 1265,
    "min_y": 1064,
    "max_y": 1207
  },
  {
    "glyph_id": 79209,
    "page_number": 488,
    "line_number": 6,
    "sura": 42,
    "ayah": 47,
    "word_position": 7,
    "min_x": 1010,
    "max_x": 1122,
    "min_y": 1090,
    "max_y": 1238
  },
  {
    "glyph_id": 79210,
    "page_number": 488,
    "line_number": 6,
    "sura": 42,
    "ayah": 47,
    "word_position": 8,
    "min_x": 937,
    "max_x": 1003,
    "min_y": 1059,
    "max_y": 1183
  },
  {
    "glyph_id": 79211,
    "page_number": 488,
    "line_number": 6,
    "sura": 42,
    "ayah": 47,
    "word_position": 9,
    "min_x": 803,
    "max_x": 926,
    "min_y": 1074,
    "max_y": 1206
  },
  {
    "glyph_id": 79212,
    "page_number": 488,
    "line_number": 6,
    "sura": 42,
    "ayah": 47,
    "word_position": 10,
    "min_x": 712,
    "max_x": 794,
    "min_y": 1069,
    "max_y": 1180
  },
  {
    "glyph_id": 79213,
    "page_number": 488,
    "line_number": 6,
    "sura": 42,
    "ayah": 47,
    "word_position": 11,
    "min_x": 503,
    "max_x": 702,
    "min_y": 1095,
    "max_y": 1209
  },
  {
    "glyph_id": 79214,
    "page_number": 488,
    "line_number": 6,
    "sura": 42,
    "ayah": 47,
    "word_position": 12,
    "min_x": 382,
    "max_x": 489,
    "min_y": 1075,
    "max_y": 1203
  },
  {
    "glyph_id": 79215,
    "page_number": 488,
    "line_number": 6,
    "sura": 42,
    "ayah": 47,
    "word_position": 13,
    "min_x": 384,
    "max_x": 364,
    "min_y": 1051,
    "max_y": 1087
  },
  {
    "glyph_id": 79216,
    "page_number": 488,
    "line_number": 6,
    "sura": 42,
    "ayah": 47,
    "word_position": 14,
    "min_x": 291,
    "max_x": 358,
    "min_y": 1090,
    "max_y": 1180
  },
  {
    "glyph_id": 79217,
    "page_number": 488,
    "line_number": 6,
    "sura": 42,
    "ayah": 47,
    "word_position": 15,
    "min_x": 108,
    "max_x": 270,
    "min_y": 1069,
    "max_y": 1239
  },
  {
    "glyph_id": 79218,
    "page_number": 488,
    "line_number": 7,
    "sura": 42,
    "ayah": 47,
    "word_position": 16,
    "min_x": 1739,
    "max_x": 1830,
    "min_y": 1300,
    "max_y": 1411
  },
  {
    "glyph_id": 79219,
    "page_number": 488,
    "line_number": 7,
    "sura": 42,
    "ayah": 47,
    "word_position": 17,
    "min_x": 1561,
    "max_x": 1733,
    "min_y": 1283,
    "max_y": 1435
  },
  {
    "glyph_id": 79220,
    "page_number": 488,
    "line_number": 7,
    "sura": 42,
    "ayah": 47,
    "word_position": 18,
    "min_x": 1355,
    "max_x": 1557,
    "min_y": 1291,
    "max_y": 1421
  },
  {
    "glyph_id": 79221,
    "page_number": 488,
    "line_number": 7,
    "sura": 42,
    "ayah": 47,
    "word_position": 19,
    "min_x": 1229,
    "max_x": 1339,
    "min_y": 1290,
    "max_y": 1400
  },
  {
    "glyph_id": 79222,
    "page_number": 488,
    "line_number": 7,
    "sura": 42,
    "ayah": 47,
    "word_position": 20,
    "min_x": 1080,
    "max_x": 1217,
    "min_y": 1268,
    "max_y": 1444
  },
  {
    "glyph_id": 79223,
    "page_number": 488,
    "line_number": 7,
    "sura": 42,
    "ayah": 47,
    "word_position": 21,
    "min_x": 973,
    "max_x": 1068,
    "min_y": 1303,
    "max_y": 1409
  },
  {
    "glyph_id": 79224,
    "page_number": 488,
    "line_number": 7,
    "sura": 42,
    "ayah": 47,
    "word_position": 22,
    "min_x": 647,
    "max_x": 966,
    "min_y": 1269,
    "max_y": 1433
  },
  {
    "glyph_id": 79225,
    "page_number": 488,
    "line_number": 7,
    "sura": 42,
    "ayah": 47,
    "word_position": 23,
    "min_x": 492,
    "max_x": 645,
    "min_y": 1271,
    "max_y": 1413
  },
  {
    "glyph_id": 79226,
    "page_number": 488,
    "line_number": 7,
    "sura": 42,
    "ayah": 48,
    "word_position": 1,
    "min_x": 358,
    "max_x": 493,
    "min_y": 1279,
    "max_y": 1420
  },
  {
    "glyph_id": 79227,
    "page_number": 488,
    "line_number": 7,
    "sura": 42,
    "ayah": 48,
    "word_position": 2,
    "min_x": 115,
    "max_x": 352,
    "min_y": 1261,
    "max_y": 1411
  },
  {
    "glyph_id": 79228,
    "page_number": 488,
    "line_number": 8,
    "sura": 42,
    "ayah": 48,
    "word_position": 3,
    "min_x": 1717,
    "max_x": 1834,
    "min_y": 1484,
    "max_y": 1585
  },
  {
    "glyph_id": 79229,
    "page_number": 488,
    "line_number": 8,
    "sura": 42,
    "ayah": 48,
    "word_position": 4,
    "min_x": 1437,
    "max_x": 1711,
    "min_y": 1465,
    "max_y": 1600
  },
  {
    "glyph_id": 79230,
    "page_number": 488,
    "line_number": 8,
    "sura": 42,
    "ayah": 48,
    "word_position": 5,
    "min_x": 1250,
    "max_x": 1426,
    "min_y": 1488,
    "max_y": 1643
  },
  {
    "glyph_id": 79231,
    "page_number": 488,
    "line_number": 8,
    "sura": 42,
    "ayah": 48,
    "word_position": 6,
    "min_x": 995,
    "max_x": 1234,
    "min_y": 1480,
    "max_y": 1610
  },
  {
    "glyph_id": 79232,
    "page_number": 488,
    "line_number": 8,
    "sura": 42,
    "ayah": 48,
    "word_position": 7,
    "min_x": 974,
    "max_x": 976,
    "min_y": 1447,
    "max_y": 1485
  },
  {
    "glyph_id": 79233,
    "page_number": 488,
    "line_number": 8,
    "sura": 42,
    "ayah": 48,
    "word_position": 8,
    "min_x": 899,
    "max_x": 970,
    "min_y": 1503,
    "max_y": 1614
  },
  {
    "glyph_id": 79234,
    "page_number": 488,
    "line_number": 8,
    "sura": 42,
    "ayah": 48,
    "word_position": 9,
    "min_x": 710,
    "max_x": 889,
    "min_y": 1486,
    "max_y": 1605
  },
  {
    "glyph_id": 79235,
    "page_number": 488,
    "line_number": 8,
    "sura": 42,
    "ayah": 48,
    "word_position": 10,
    "min_x": 596,
    "max_x": 692,
    "min_y": 1468,
    "max_y": 1619
  },
  {
    "glyph_id": 79236,
    "page_number": 488,
    "line_number": 8,
    "sura": 42,
    "ayah": 48,
    "word_position": 11,
    "min_x": 385,
    "max_x": 577,
    "min_y": 1479,
    "max_y": 1647
  },
  {
    "glyph_id": 79237,
    "page_number": 488,
    "line_number": 8,
    "sura": 42,
    "ayah": 48,
    "word_position": 12,
    "min_x": 388,
    "max_x": 379,
    "min_y": 1439,
    "max_y": 1476
  },
  {
    "glyph_id": 79238,
    "page_number": 488,
    "line_number": 8,
    "sura": 42,
    "ayah": 48,
    "word_position": 13,
    "min_x": 210,
    "max_x": 373,
    "min_y": 1480,
    "max_y": 1624
  },
  {
    "glyph_id": 79239,
    "page_number": 488,
    "line_number": 8,
    "sura": 42,
    "ayah": 48,
    "word_position": 14,
    "min_x": 105,
    "max_x": 204,
    "min_y": 1478,
    "max_y": 1617
  },
  {
    "glyph_id": 79240,
    "page_number": 488,
    "line_number": 9,
    "sura": 42,
    "ayah": 48,
    "word_position": 15,
    "min_x": 1659,
    "max_x": 1830,
    "min_y": 1674,
    "max_y": 1787
  },
  {
    "glyph_id": 79241,
    "page_number": 488,
    "line_number": 9,
    "sura": 42,
    "ayah": 48,
    "word_position": 16,
    "min_x": 1371,
    "max_x": 1643,
    "min_y": 1676,
    "max_y": 1820
  },
  {
    "glyph_id": 79242,
    "page_number": 488,
    "line_number": 9,
    "sura": 42,
    "ayah": 48,
    "word_position": 17,
    "min_x": 1259,
    "max_x": 1354,
    "min_y": 1688,
    "max_y": 1809
  },
  {
    "glyph_id": 79243,
    "page_number": 488,
    "line_number": 9,
    "sura": 42,
    "ayah": 48,
    "word_position": 18,
    "min_x": 1041,
    "max_x": 1244,
    "min_y": 1679,
    "max_y": 1805
  },
  {
    "glyph_id": 79244,
    "page_number": 488,
    "line_number": 9,
    "sura": 42,
    "ayah": 48,
    "word_position": 19,
    "min_x": 886,
    "max_x": 1026,
    "min_y": 1690,
    "max_y": 1837
  },
  {
    "glyph_id": 79245,
    "page_number": 488,
    "line_number": 9,
    "sura": 42,
    "ayah": 48,
    "word_position": 20,
    "min_x": 768,
    "max_x": 866,
    "min_y": 1697,
    "max_y": 1822
  },
  {
    "glyph_id": 79246,
    "page_number": 488,
    "line_number": 9,
    "sura": 42,
    "ayah": 48,
    "word_position": 21,
    "min_x": 753,
    "max_x": 759,
    "min_y": 1664,
    "max_y": 1703
  },
  {
    "glyph_id": 79247,
    "page_number": 488,
    "line_number": 9,
    "sura": 42,
    "ayah": 48,
    "word_position": 22,
    "min_x": 620,
    "max_x": 753,
    "min_y": 1693,
    "max_y": 1822
  },
  {
    "glyph_id": 79248,
    "page_number": 488,
    "line_number": 9,
    "sura": 42,
    "ayah": 48,
    "word_position": 23,
    "min_x": 367,
    "max_x": 610,
    "min_y": 1675,
    "max_y": 1850
  },
  {
    "glyph_id": 79249,
    "page_number": 488,
    "line_number": 9,
    "sura": 42,
    "ayah": 48,
    "word_position": 24,
    "min_x": 109,
    "max_x": 350,
    "min_y": 1661,
    "max_y": 1823
  },
  {
    "glyph_id": 79250,
    "page_number": 488,
    "line_number": 10,
    "sura": 42,
    "ayah": 48,
    "word_position": 25,
    "min_x": 1727,
    "max_x": 1829,
    "min_y": 1898,
    "max_y": 2020
  },
  {
    "glyph_id": 79251,
    "page_number": 488,
    "line_number": 10,
    "sura": 42,
    "ayah": 48,
    "word_position": 26,
    "min_x": 1488,
    "max_x": 1716,
    "min_y": 1874,
    "max_y": 1990
  },
  {
    "glyph_id": 79252,
    "page_number": 488,
    "line_number": 10,
    "sura": 42,
    "ayah": 48,
    "word_position": 27,
    "min_x": 1226,
    "max_x": 1475,
    "min_y": 1866,
    "max_y": 2037
  },
  {
    "glyph_id": 79253,
    "page_number": 488,
    "line_number": 10,
    "sura": 42,
    "ayah": 48,
    "word_position": 28,
    "min_x": 1096,
    "max_x": 1211,
    "min_y": 1872,
    "max_y": 2022
  },
  {
    "glyph_id": 79254,
    "page_number": 488,
    "line_number": 10,
    "sura": 42,
    "ayah": 48,
    "word_position": 29,
    "min_x": 804,
    "max_x": 1080,
    "min_y": 1879,
    "max_y": 2021
  },
  {
    "glyph_id": 79255,
    "page_number": 488,
    "line_number": 10,
    "sura": 42,
    "ayah": 48,
    "word_position": 30,
    "min_x": 602,
    "max_x": 786,
    "min_y": 1873,
    "max_y": 2014
  },
  {
    "glyph_id": 79256,
    "page_number": 488,
    "line_number": 10,
    "sura": 42,
    "ayah": 48,
    "word_position": 31,
    "min_x": 451,
    "max_x": 604,
    "min_y": 1875,
    "max_y": 2017
  },
  {
    "glyph_id": 79257,
    "page_number": 488,
    "line_number": 10,
    "sura": 42,
    "ayah": 49,
    "word_position": 1,
    "min_x": 343,
    "max_x": 452,
    "min_y": 1882,
    "max_y": 2008
  },
  {
    "glyph_id": 79258,
    "page_number": 488,
    "line_number": 10,
    "sura": 42,
    "ayah": 49,
    "word_position": 2,
    "min_x": 100,
    "max_x": 327,
    "min_y": 1885,
    "max_y": 1996
  },
  {
    "glyph_id": 79259,
    "page_number": 488,
    "line_number": 11,
    "sura": 42,
    "ayah": 49,
    "word_position": 3,
    "min_x": 1513,
    "max_x": 1833,
    "min_y": 2088,
    "max_y": 2218
  },
  {
    "glyph_id": 79260,
    "page_number": 488,
    "line_number": 11,
    "sura": 42,
    "ayah": 49,
    "word_position": 4,
    "min_x": 1207,
    "max_x": 1492,
    "min_y": 2066,
    "max_y": 2205
  },
  {
    "glyph_id": 79261,
    "page_number": 488,
    "line_number": 11,
    "sura": 42,
    "ayah": 49,
    "word_position": 5,
    "min_x": 1193,
    "max_x": 1193,
    "min_y": 2082,
    "max_y": 2117
  },
  {
    "glyph_id": 79262,
    "page_number": 488,
    "line_number": 11,
    "sura": 42,
    "ayah": 49,
    "word_position": 6,
    "min_x": 1021,
    "max_x": 1187,
    "min_y": 2075,
    "max_y": 2213
  },
  {
    "glyph_id": 79263,
    "page_number": 488,
    "line_number": 11,
    "sura": 42,
    "ayah": 49,
    "word_position": 7,
    "min_x": 940,
    "max_x": 1009,
    "min_y": 2088,
    "max_y": 2184
  },
  {
    "glyph_id": 79264,
    "page_number": 488,
    "line_number": 11,
    "sura": 42,
    "ayah": 49,
    "word_position": 8,
    "min_x": 773,
    "max_x": 930,
    "min_y": 2079,
    "max_y": 2200
  },
  {
    "glyph_id": 79265,
    "page_number": 488,
    "line_number": 11,
    "sura": 42,
    "ayah": 49,
    "word_position": 9,
    "min_x": 773,
    "max_x": 757,
    "min_y": 2049,
    "max_y": 2085
  },
  {
    "glyph_id": 79266,
    "page_number": 488,
    "line_number": 11,
    "sura": 42,
    "ayah": 49,
    "word_position": 10,
    "min_x": 590,
    "max_x": 751,
    "min_y": 2096,
    "max_y": 2217
  },
  {
    "glyph_id": 79267,
    "page_number": 488,
    "line_number": 11,
    "sura": 42,
    "ayah": 49,
    "word_position": 11,
    "min_x": 450,
    "max_x": 575,
    "min_y": 2095,
    "max_y": 2217
  },
  {
    "glyph_id": 79268,
    "page_number": 488,
    "line_number": 11,
    "sura": 42,
    "ayah": 49,
    "word_position": 12,
    "min_x": 295,
    "max_x": 441,
    "min_y": 2084,
    "max_y": 2214
  },
  {
    "glyph_id": 79269,
    "page_number": 488,
    "line_number": 11,
    "sura": 42,
    "ayah": 49,
    "word_position": 13,
    "min_x": 112,
    "max_x": 284,
    "min_y": 2076,
    "max_y": 2218
  },
  {
    "glyph_id": 79270,
    "page_number": 488,
    "line_number": 12,
    "sura": 42,
    "ayah": 49,
    "word_position": 14,
    "min_x": 1595,
    "max_x": 1828,
    "min_y": 2303,
    "max_y": 2412
  },
  {
    "glyph_id": 79271,
    "page_number": 488,
    "line_number": 12,
    "sura": 42,
    "ayah": 49,
    "word_position": 15,
    "min_x": 1451,
    "max_x": 1587,
    "min_y": 2297,
    "max_y": 2416
  },
  {
    "glyph_id": 79272,
    "page_number": 488,
    "line_number": 12,
    "sura": 42,
    "ayah": 49,
    "word_position": 16,
    "min_x": 1304,
    "max_x": 1449,
    "min_y": 2285,
    "max_y": 2415
  },
  {
    "glyph_id": 79273,
    "page_number": 488,
    "line_number": 12,
    "sura": 42,
    "ayah": 49,
    "word_position": 17,
    "min_x": 1065,
    "max_x": 1298,
    "min_y": 2263,
    "max_y": 2410
  },
  {
    "glyph_id": 79274,
    "page_number": 488,
    "line_number": 12,
    "sura": 42,
    "ayah": 49,
    "word_position": 18,
    "min_x": 908,
    "max_x": 1061,
    "min_y": 2277,
    "max_y": 2419
  },
  {
    "glyph_id": 79275,
    "page_number": 488,
    "line_number": 12,
    "sura": 42,
    "ayah": 50,
    "word_position": 1,
    "min_x": 813,
    "max_x": 909,
    "min_y": 2281,
    "max_y": 2413
  },
  {
    "glyph_id": 79276,
    "page_number": 488,
    "line_number": 12,
    "sura": 42,
    "ayah": 50,
    "word_position": 2,
    "min_x": 525,
    "max_x": 814,
    "min_y": 2286,
    "max_y": 2443
  },
  {
    "glyph_id": 79277,
    "page_number": 488,
    "line_number": 12,
    "sura": 42,
    "ayah": 50,
    "word_position": 3,
    "min_x": 339,
    "max_x": 512,
    "min_y": 2274,
    "max_y": 2415
  },
  {
    "glyph_id": 79278,
    "page_number": 488,
    "line_number": 12,
    "sura": 42,
    "ayah": 50,
    "word_position": 4,
    "min_x": 110,
    "max_x": 333,
    "min_y": 2282,
    "max_y": 2409
  },
  {
    "glyph_id": 79279,
    "page_number": 488,
    "line_number": 12,
    "sura": 42,
    "ayah": 50,
    "word_position": 5,
    "min_x": 104,
    "max_x": 108,
    "min_y": 2255,
    "max_y": 2293
  },
  {
    "glyph_id": 79280,
    "page_number": 488,
    "line_number": 13,
    "sura": 42,
    "ayah": 50,
    "word_position": 6,
    "min_x": 1586,
    "max_x": 1833,
    "min_y": 2484,
    "max_y": 2610
  },
  {
    "glyph_id": 79281,
    "page_number": 488,
    "line_number": 13,
    "sura": 42,
    "ayah": 50,
    "word_position": 7,
    "min_x": 1486,
    "max_x": 1576,
    "min_y": 2496,
    "max_y": 2607
  },
  {
    "glyph_id": 79282,
    "page_number": 488,
    "line_number": 13,
    "sura": 42,
    "ayah": 50,
    "word_position": 8,
    "min_x": 1333,
    "max_x": 1478,
    "min_y": 2486,
    "max_y": 2616
  },
  {
    "glyph_id": 79283,
    "page_number": 488,
    "line_number": 13,
    "sura": 42,
    "ayah": 50,
    "word_position": 9,
    "min_x": 1097,
    "max_x": 1325,
    "min_y": 2490,
    "max_y": 2613
  },
  {
    "glyph_id": 79284,
    "page_number": 488,
    "line_number": 13,
    "sura": 42,
    "ayah": 50,
    "word_position": 10,
    "min_x": 1079,
    "max_x": 1083,
    "min_y": 2461,
    "max_y": 2497
  },
  {
    "glyph_id": 79285,
    "page_number": 488,
    "line_number": 13,
    "sura": 42,
    "ayah": 50,
    "word_position": 11,
    "min_x": 959,
    "max_x": 1077,
    "min_y": 2476,
    "max_y": 2623
  },
  {
    "glyph_id": 79286,
    "page_number": 488,
    "line_number": 13,
    "sura": 42,
    "ayah": 50,
    "word_position": 12,
    "min_x": 775,
    "max_x": 952,
    "min_y": 2493,
    "max_y": 2625
  },
  {
    "glyph_id": 79287,
    "page_number": 488,
    "line_number": 13,
    "sura": 42,
    "ayah": 50,
    "word_position": 13,
    "min_x": 625,
    "max_x": 774,
    "min_y": 2480,
    "max_y": 2620
  },
  {
    "glyph_id": 79288,
    "page_number": 488,
    "line_number": 13,
    "sura": 42,
    "ayah": 50,
    "word_position": 14,
    "min_x": 465,
    "max_x": 619,
    "min_y": 2477,
    "max_y": 2619
  },
  {
    "glyph_id": 79289,
    "page_number": 488,
    "line_number": 13,
    "sura": 42,
    "ayah": 51,
    "word_position": 1,
    "min_x": 351,
    "max_x": 466,
    "min_y": 2504,
    "max_y": 2612
  },
  {
    "glyph_id": 79290,
    "page_number": 488,
    "line_number": 13,
    "sura": 42,
    "ayah": 51,
    "word_position": 2,
    "min_x": 230,
    "max_x": 328,
    "min_y": 2500,
    "max_y": 2611
  },
  {
    "glyph_id": 79291,
    "page_number": 488,
    "line_number": 13,
    "sura": 42,
    "ayah": 51,
    "word_position": 3,
    "min_x": 113,
    "max_x": 211,
    "min_y": 2473,
    "max_y": 2598
  },
  {
    "glyph_id": 79292,
    "page_number": 488,
    "line_number": 14,
    "sura": 42,
    "ayah": 51,
    "word_position": 4,
    "min_x": 1671,
    "max_x": 1834,
    "min_y": 2693,
    "max_y": 2846
  },
  {
    "glyph_id": 79293,
    "page_number": 488,
    "line_number": 14,
    "sura": 42,
    "ayah": 51,
    "word_position": 5,
    "min_x": 1592,
    "max_x": 1667,
    "min_y": 2673,
    "max_y": 2800
  },
  {
    "glyph_id": 79294,
    "page_number": 488,
    "line_number": 14,
    "sura": 42,
    "ayah": 51,
    "word_position": 6,
    "min_x": 1355,
    "max_x": 1579,
    "min_y": 2681,
    "max_y": 2818
  },
  {
    "glyph_id": 79295,
    "page_number": 488,
    "line_number": 14,
    "sura": 42,
    "ayah": 51,
    "word_position": 7,
    "min_x": 1228,
    "max_x": 1340,
    "min_y": 2684,
    "max_y": 2792
  },
  {
    "glyph_id": 79296,
    "page_number": 488,
    "line_number": 14,
    "sura": 42,
    "ayah": 51,
    "word_position": 8,
    "min_x": 1125,
    "max_x": 1219,
    "min_y": 2664,
    "max_y": 2822
  },
  {
    "glyph_id": 79297,
    "page_number": 488,
    "line_number": 14,
    "sura": 42,
    "ayah": 51,
    "word_position": 9,
    "min_x": 957,
    "max_x": 1113,
    "min_y": 2688,
    "max_y": 2813
  },
  {
    "glyph_id": 79298,
    "page_number": 488,
    "line_number": 14,
    "sura": 42,
    "ayah": 51,
    "word_position": 10,
    "min_x": 861,
    "max_x": 940,
    "min_y": 2679,
    "max_y": 2819
  },
  {
    "glyph_id": 79299,
    "page_number": 488,
    "line_number": 14,
    "sura": 42,
    "ayah": 51,
    "word_position": 11,
    "min_x": 749,
    "max_x": 861,
    "min_y": 2745,
    "max_y": 2811
  },
  {
    "glyph_id": 79300,
    "page_number": 488,
    "line_number": 14,
    "sura": 42,
    "ayah": 51,
    "word_position": 12,
    "min_x": 574,
    "max_x": 741,
    "min_y": 2687,
    "max_y": 2838
  },
  {
    "glyph_id": 79301,
    "page_number": 488,
    "line_number": 14,
    "sura": 42,
    "ayah": 51,
    "word_position": 13,
    "min_x": 380,
    "max_x": 569,
    "min_y": 2686,
    "max_y": 2834
  },
  {
    "glyph_id": 79302,
    "page_number": 488,
    "line_number": 14,
    "sura": 42,
    "ayah": 51,
    "word_position": 14,
    "min_x": 289,
    "max_x": 371,
    "min_y": 2667,
    "max_y": 2811
  },
  {
    "glyph_id": 79303,
    "page_number": 488,
    "line_number": 14,
    "sura": 42,
    "ayah": 51,
    "word_position": 15,
    "min_x": 103,
    "max_x": 286,
    "min_y": 2686,
    "max_y": 2827
  },
  {
    "glyph_id": 79304,
    "page_number": 488,
    "line_number": 15,
    "sura": 42,
    "ayah": 51,
    "word_position": 16,
    "min_x": 1621,
    "max_x": 1830,
    "min_y": 2881,
    "max_y": 3018
  },
  {
    "glyph_id": 79305,
    "page_number": 488,
    "line_number": 15,
    "sura": 42,
    "ayah": 51,
    "word_position": 17,
    "min_x": 1364,
    "max_x": 1611,
    "min_y": 2884,
    "max_y": 3032
  },
  {
    "glyph_id": 79306,
    "page_number": 488,
    "line_number": 15,
    "sura": 42,
    "ayah": 51,
    "word_position": 18,
    "min_x": 1126,
    "max_x": 1348,
    "min_y": 2889,
    "max_y": 3032
  },
  {
    "glyph_id": 79307,
    "page_number": 488,
    "line_number": 15,
    "sura": 42,
    "ayah": 51,
    "word_position": 19,
    "min_x": 1047,
    "max_x": 1114,
    "min_y": 2894,
    "max_y": 2990
  },
  {
    "glyph_id": 79308,
    "page_number": 488,
    "line_number": 15,
    "sura": 42,
    "ayah": 51,
    "word_position": 20,
    "min_x": 893,
    "max_x": 1038,
    "min_y": 2888,
    "max_y": 3018
  },
  {
    "glyph_id": 79309,
    "page_number": 488,
    "line_number": 15,
    "sura": 42,
    "ayah": 51,
    "word_position": 21,
    "min_x": 895,
    "max_x": 884,
    "min_y": 2850,
    "max_y": 2886
  },
  {
    "glyph_id": 79310,
    "page_number": 488,
    "line_number": 15,
    "sura": 42,
    "ayah": 51,
    "word_position": 22,
    "min_x": 753,
    "max_x": 878,
    "min_y": 2877,
    "max_y": 3023
  },
  {
    "glyph_id": 79311,
    "page_number": 488,
    "line_number": 15,
    "sura": 42,
    "ayah": 51,
    "word_position": 23,
    "min_x": 630,
    "max_x": 748,
    "min_y": 2879,
    "max_y": 3027
  },
  {
    "glyph_id": 79312,
    "page_number": 488,
    "line_number": 15,
    "sura": 42,
    "ayah": 51,
    "word_position": 24,
    "min_x": 267,
    "max_x": 622,
    "min_y": 2899,
    "max_y": 3016
  },
  {
    "glyph_id": 79313,
    "page_number": 488,
    "line_number": 15,
    "sura": 42,
    "ayah": 51,
    "word_position": 25,
    "min_x": 97,
    "max_x": 250,
    "min_y": 2880,
    "max_y": 3022
  }
]